ergo3d/__init__.py
ergo3d/camera/Camera.py
ergo3d/camera/FLIR_camera.py
ergo3d/camera/__init__.py
ergo3d/camera/checkerboard_camera.py
ergo3d/camera/theia3d_camera.py
ergo3d/geometry/CoordinateSystem3D.py
ergo3d/geometry/JointAngles.py
ergo3d/geometry/Plane.py
ergo3d/geometry/Point.py
ergo3d/geometry/__init__.py
ergo3d/geometryPytorch/CoordinateSystem3D.py
ergo3d/geometryPytorch/JointAngles.py
ergo3d/geometryPytorch/Plane.py
ergo3d/geometryPytorch/Point.py
ergo3d/geometryPytorch/__init__.py
ergo3d-0.2.0.dist-info/LICENSE
ergo3d-0.2.0.dist-info/METADATA
ergo3d-0.2.0.dist-info/WHEEL
ergo3d-0.2.0.dist-info/top_level.txt
ergo3d-0.2.0.dist-info/RECORD
